pytest_black.py
pytest_black-0.5.0.dist-info/LICENSE
pytest_black-0.5.0.dist-info/METADATA
pytest_black-0.5.0.dist-info/WHEEL
pytest_black-0.5.0.dist-info/entry_points.txt
pytest_black-0.5.0.dist-info/top_level.txt
pytest_black-0.5.0.dist-info/RECORD
