Metadata-Version: 2.1
Name: pytest-black
Version: 0.5.0
Summary: A pytest plugin to enable format checking with black
Home-page: https://github.com/coherent-oss/pytest-black
Author: ShopKeep, Inc.
Author-email: oss@shopkeep.com
Maintainer: Jason R. Coombs
Maintainer-email: jaraco@jaraco.com
License: MIT
Classifier: Development Status :: 4 - Beta
Classifier: Framework :: Pytest
Classifier: Intended Audience :: Developers
Classifier: Topic :: Software Development :: Testing
Classifier: Programming Language :: Python :: 3
Classifier: Operating System :: OS Independent
Classifier: License :: OSI Approved :: MIT License
Requires-Python: >=3.5
License-File: LICENSE
Requires-Dist: pytest>=7.0.0
Requires-Dist: black; python_version >= "3.6"
Requires-Dist: toml
